{"data":[{"ayah":"187","block":"1","height":"62.0","left":"3.0","surah":"3","top":"49.0","width":"773.0"},{"ayah":"187","block":"2","height":"62.0","left":"3.0","surah":"3","top":"148.0","width":"773.0"},{"ayah":"187","block":"3","height":"62.0","left":"371.0","surah":"3","top":"249.0","width":"405.0"},{"ayah":"188","block":"1","height":"62.0","left":"3.0","surah":"3","top":"249.0","width":"368.0"},{"ayah":"188","block":"2","height":"62.0","left":"3.0","surah":"3","top":"345.0","width":"773.0"},{"ayah":"188","block":"3","height":"62.0","left":"180.0","surah":"3","top":"446.0","width":"596.0"},{"ayah":"189","block":"1","height":"62.0","left":"3.0","surah":"3","top":"446.0","width":"177.0"},{"ayah":"189","block":"2","height":"62.0","left":"105.0","surah":"3","top":"542.0","width":"671.0"},{"ayah":"190","block":"1","height":"62.0","left":"3.0","surah":"3","top":"542.0","width":"102.0"},{"ayah":"190","block":"2","height":"62.0","left":"3.0","surah":"3","top":"641.0","width":"773.0"},{"ayah":"190","block":"3","height":"62.0","left":"506.0","surah":"3","top":"739.0","width":"270.0"},{"ayah":"191","block":"1","height":"62.0","left":"3.0","surah":"3","top":"739.0","width":"503.0"},{"ayah":"191","block":"2","height":"62.0","left":"3.0","surah":"3","top":"838.0","width":"773.0"},{"ayah":"191","block":"3","height":"62.0","left":"3.0","surah":"3","top":"936.0","width":"773.0"},{"ayah":"192","block":"1","height":"62.0","left":"3.0","surah":"3","top":"1035.0","width":"773.0"},{"ayah":"192","block":"2","height":"62.0","left":"575.0","surah":"3","top":"1133.0","width":"201.0"},{"ayah":"193","block":"1","height":"62.0","left":"3.0","surah":"3","top":"1133.0","width":"572.0"},{"ayah":"193","block":"2","height":"62.0","left":"3.0","surah":"3","top":"1230.0","width":"773.0"},{"ayah":"193","block":"3","height":"62.0","left":"339.0","surah":"3","top":"1332.0","width":"438.0"},{"ayah":"194","block":"1","height":"62.0","left":"3.0","surah":"3","top":"1332.0","width":"335.0"},{"ayah":"194","block":"2","height":"62.0","left":"3.0","surah":"3","top":"1427.0","width":"773.0"}],"viewportHeight":"1327","viewportWidth":"800"}