{"data":[{"ayah":"62","block":"1","height":"62.0","left":"22.0","surah":"10","top":"51.0","width":"770.0"},{"ayah":"62","block":"2","height":"62.0","left":"699.0","surah":"10","top":"150.0","width":"63.0"},{"ayah":"63","block":"1","height":"62.0","left":"209.0","surah":"10","top":"150.0","width":"488.0"},{"ayah":"64","block":"1","height":"62.0","left":"22.0","surah":"10","top":"150.0","width":"185.0"},{"ayah":"64","block":"2","height":"62.0","left":"22.0","surah":"10","top":"250.0","width":"770.0"},{"ayah":"64","block":"3","height":"62.0","left":"417.0","surah":"10","top":"346.0","width":"375.0"},{"ayah":"65","block":"1","height":"62.0","left":"22.0","surah":"10","top":"346.0","width":"387.0"},{"ayah":"65","block":"2","height":"62.0","left":"204.0","surah":"10","top":"446.0","width":"588.0"},{"ayah":"66","block":"1","height":"62.0","left":"22.0","surah":"10","top":"446.0","width":"173.0"},{"ayah":"66","block":"2","height":"62.0","left":"22.0","surah":"10","top":"542.0","width":"770.0"},{"ayah":"66","block":"3","height":"62.0","left":"22.0","surah":"10","top":"639.0","width":"770.0"},{"ayah":"66","block":"4","height":"62.0","left":"362.0","surah":"10","top":"737.0","width":"430.0"},{"ayah":"67","block":"1","height":"62.0","left":"22.0","surah":"10","top":"737.0","width":"335.0"},{"ayah":"67","block":"2","height":"62.0","left":"22.0","surah":"10","top":"835.0","width":"770.0"},{"ayah":"67","block":"3","height":"62.0","left":"363.0","surah":"10","top":"933.0","width":"429.0"},{"ayah":"68","block":"1","height":"62.0","left":"22.0","surah":"10","top":"933.0","width":"337.0"},{"ayah":"68","block":"2","height":"62.0","left":"22.0","surah":"10","top":"1031.0","width":"770.0"},{"ayah":"68","block":"3","height":"62.0","left":"22.0","surah":"10","top":"1128.0","width":"770.0"},{"ayah":"68","block":"4","height":"62.0","left":"564.0","surah":"10","top":"1224.0","width":"228.0"},{"ayah":"69","block":"1","height":"62.0","left":"22.0","surah":"10","top":"1224.0","width":"540.0"},{"ayah":"69","block":"2","height":"62.0","left":"541.0","surah":"10","top":"1326.0","width":"251.0"},{"ayah":"70","block":"1","height":"62.0","left":"22.0","surah":"10","top":"1326.0","width":"514.0"},{"ayah":"70","block":"2","height":"62.0","left":"55.0","surah":"10","top":"1420.0","width":"737.0"}],"viewportHeight":"1327","viewportWidth":"800"}