{"data":[{"ayah":"54","block":"1","height":"62.0","left":"9.0","surah":"24","top":"52.0","width":"768.0"},{"ayah":"54","block":"2","height":"62.0","left":"9.0","surah":"24","top":"151.0","width":"768.0"},{"ayah":"54","block":"3","height":"62.0","left":"492.0","surah":"24","top":"251.0","width":"285.0"},{"ayah":"55","block":"1","height":"62.0","left":"9.0","surah":"24","top":"251.0","width":"483.0"},{"ayah":"55","block":"2","height":"62.0","left":"9.0","surah":"24","top":"347.0","width":"768.0"},{"ayah":"55","block":"3","height":"62.0","left":"9.0","surah":"24","top":"447.0","width":"768.0"},{"ayah":"55","block":"4","height":"62.0","left":"9.0","surah":"24","top":"542.0","width":"768.0"},{"ayah":"55","block":"5","height":"62.0","left":"9.0","surah":"24","top":"640.0","width":"768.0"},{"ayah":"56","block":"1","height":"62.0","left":"9.0","surah":"24","top":"737.0","width":"768.0"},{"ayah":"56","block":"2","height":"62.0","left":"616.0","surah":"24","top":"835.0","width":"161.0"},{"ayah":"57","block":"1","height":"62.0","left":"9.0","surah":"24","top":"835.0","width":"607.0"},{"ayah":"57","block":"2","height":"62.0","left":"289.0","surah":"24","top":"933.0","width":"488.0"},{"ayah":"58","block":"1","height":"62.0","left":"9.0","surah":"24","top":"933.0","width":"280.0"},{"ayah":"58","block":"2","height":"62.0","left":"9.0","surah":"24","top":"1031.0","width":"768.0"},{"ayah":"58","block":"3","height":"62.0","left":"9.0","surah":"24","top":"1128.0","width":"768.0"},{"ayah":"58","block":"4","height":"62.0","left":"9.0","surah":"24","top":"1224.0","width":"768.0"},{"ayah":"58","block":"5","height":"62.0","left":"9.0","surah":"24","top":"1326.0","width":"768.0"},{"ayah":"58","block":"6","height":"62.0","left":"9.0","surah":"24","top":"1420.0","width":"768.0"}],"viewportHeight":"1327","viewportWidth":"800"}