{"data":[{"ayah":"158","block":"1","height":"62.0","left":"258.0","surah":"3","top":"49.0","width":"524.0"},{"ayah":"159","block":"1","height":"62.0","left":"3.0","surah":"3","top":"49.0","width":"255.0"},{"ayah":"159","block":"2","height":"62.0","left":"3.0","surah":"3","top":"149.0","width":"779.0"},{"ayah":"159","block":"3","height":"62.0","left":"3.0","surah":"3","top":"250.0","width":"779.0"},{"ayah":"159","block":"4","height":"62.0","left":"220.0","surah":"3","top":"347.0","width":"562.0"},{"ayah":"160","block":"1","height":"62.0","left":"3.0","surah":"3","top":"347.0","width":"217.0"},{"ayah":"160","block":"2","height":"62.0","left":"3.0","surah":"3","top":"449.0","width":"779.0"},{"ayah":"160","block":"3","height":"62.0","left":"291.0","surah":"3","top":"546.0","width":"491.0"},{"ayah":"161","block":"1","height":"62.0","left":"3.0","surah":"3","top":"546.0","width":"288.0"},{"ayah":"161","block":"2","height":"62.0","left":"3.0","surah":"3","top":"645.0","width":"779.0"},{"ayah":"161","block":"3","height":"62.0","left":"335.0","surah":"3","top":"744.0","width":"477.0"},{"ayah":"162","block":"1","height":"62.0","left":"3.0","surah":"3","top":"744.0","width":"332.0"},{"ayah":"162","block":"2","height":"62.0","left":"3.0","surah":"3","top":"843.0","width":"779.0"},{"ayah":"162","block":"3","height":"62.0","left":"696.0","surah":"3","top":"942.0","width":"86.0"},{"ayah":"163","block":"1","height":"62.0","left":"3.0","surah":"3","top":"942.0","width":"693.0"},{"ayah":"164","block":"1","height":"62.0","left":"3.0","surah":"3","top":"1042.0","width":"779.0"},{"ayah":"164","block":"2","height":"62.0","left":"3.0","surah":"3","top":"1141.0","width":"779.0"},{"ayah":"164","block":"3","height":"62.0","left":"121.0","surah":"3","top":"1238.0","width":"661.0"},{"ayah":"165","block":"1","height":"62.0","left":"3.0","surah":"3","top":"1238.0","width":"118.0"},{"ayah":"165","block":"2","height":"62.0","left":"3.0","surah":"3","top":"1341.0","width":"779.0"},{"ayah":"165","block":"3","height":"62.0","left":"3.0","surah":"3","top":"1436.0","width":"779.0"}],"viewportHeight":"1327","viewportWidth":"800"}