{"data":[{"ayah":"7","block":"1","height":"62.0","left":"22.0","surah":"9","top":"51.0","width":"770.0"},{"ayah":"7","block":"2","height":"62.0","left":"22.0","surah":"9","top":"150.0","width":"770.0"},{"ayah":"7","block":"3","height":"62.0","left":"22.0","surah":"9","top":"250.0","width":"770.0"},{"ayah":"7","block":"4","height":"62.0","left":"696.0","surah":"9","top":"346.0","width":"86.0"},{"ayah":"8","block":"1","height":"62.0","left":"22.0","surah":"9","top":"346.0","width":"673.0"},{"ayah":"8","block":"2","height":"62.0","left":"22.0","surah":"9","top":"446.0","width":"770.0"},{"ayah":"8","block":"3","height":"62.0","left":"568.0","surah":"9","top":"541.0","width":"224.0"},{"ayah":"9","block":"1","height":"62.0","left":"22.0","surah":"9","top":"541.0","width":"546.0"},{"ayah":"9","block":"2","height":"62.0","left":"189.0","surah":"9","top":"639.0","width":"603.0"},{"ayah":"10","block":"1","height":"62.0","left":"22.0","surah":"9","top":"639.0","width":"166.0"},{"ayah":"10","block":"2","height":"62.0","left":"54.0","surah":"9","top":"737.0","width":"738.0"},{"ayah":"11","block":"1","height":"62.0","left":"22.0","surah":"9","top":"835.0","width":"770.0"},{"ayah":"11","block":"2","height":"62.0","left":"179.0","surah":"9","top":"932.0","width":"613.0"},{"ayah":"12","block":"1","height":"62.0","left":"22.0","surah":"9","top":"932.0","width":"150.0"},{"ayah":"12","block":"2","height":"62.0","left":"22.0","surah":"9","top":"1030.0","width":"770.0"},{"ayah":"12","block":"3","height":"62.0","left":"22.0","surah":"9","top":"1128.0","width":"770.0"},{"ayah":"12","block":"4","height":"62.0","left":"703.0","surah":"9","top":"1224.0","width":"89.0"},{"ayah":"13","block":"1","height":"62.0","left":"22.0","surah":"9","top":"1224.0","width":"676.0"},{"ayah":"13","block":"2","height":"62.0","left":"22.0","surah":"9","top":"1325.0","width":"770.0"},{"ayah":"13","block":"3","height":"62.0","left":"53.0","surah":"9","top":"1420.0","width":"739.0"}],"viewportHeight":"1327","viewportWidth":"800"}