{"data":[{"ayah":"87","block":"1","height":"80.0","left":"44.0","surah":"4","top":"64.0","width":"748.0"},{"ayah":"87","block":"2","height":"80.0","left":"361.0","surah":"4","top":"144.0","width":"431.0"},{"ayah":"88","block":"1","height":"80.0","left":"44.0","surah":"4","top":"144.0","width":"317.0"},{"ayah":"88","block":"2","height":"80.0","left":"44.0","surah":"4","top":"225.0","width":"748.0"},{"ayah":"88","block":"3","height":"80.0","left":"142.0","surah":"4","top":"306.0","width":"650.0"},{"ayah":"89","block":"1","height":"80.0","left":"44.0","surah":"4","top":"306.0","width":"98.0"},{"ayah":"89","block":"2","height":"80.0","left":"44.0","surah":"4","top":"387.0","width":"748.0"},{"ayah":"89","block":"3","height":"80.0","left":"44.0","surah":"4","top":"468.0","width":"748.0"},{"ayah":"89","block":"4","height":"80.0","left":"44.0","surah":"4","top":"549.0","width":"748.0"},{"ayah":"90","block":"1","height":"80.0","left":"44.0","surah":"4","top":"630.0","width":"748.0"},{"ayah":"90","block":"2","height":"80.0","left":"44.0","surah":"4","top":"711.0","width":"748.0"},{"ayah":"90","block":"3","height":"80.0","left":"44.0","surah":"4","top":"792.0","width":"748.0"},{"ayah":"90","block":"4","height":"80.0","left":"44.0","surah":"4","top":"873.0","width":"748.0"},{"ayah":"91","block":"1","height":"80.0","left":"44.0","surah":"4","top":"953.0","width":"748.0"},{"ayah":"91","block":"2","height":"80.0","left":"44.0","surah":"4","top":"1034.0","width":"748.0"},{"ayah":"91","block":"3","height":"80.0","left":"44.0","surah":"4","top":"1115.0","width":"748.0"},{"ayah":"91","block":"4","height":"87.0","left":"44.0","surah":"4","top":"1196.0","width":"748.0"}],"viewportHeight":"1327","viewportWidth":"800"}