{"data": [{"ayah": "24","block": "1","height": "144","left": "56","surah": "4","top": "64","width": "1002"},{"ayah": "24","block": "2","height": "137","left": "56","surah": "4","top": "208","width": "1002"},{"ayah": "24","block": "3","height": "135","left": "56","surah": "4","top": "345","width": "1002"},{"ayah": "24","block": "4","height": "138","left": "56","surah": "4","top": "480","width": "1002"},{"ayah": "24","block": "5","height": "136","left": "56","surah": "4","top": "618","width": "1002"},{"ayah": "24","block": "6","height": "136","left": "793","surah": "4","top": "754","width": "265"},{"ayah": "25","block": "1","height": "136","left": "56","surah": "4","top": "754","width": "736"},{"ayah": "25","block": "2","height": "137","left": "56","surah": "4","top": "890","width": "1002"},{"ayah": "25","block": "3","height": "135","left": "56","surah": "4","top": "1027","width": "1002"},{"ayah": "25","block": "4","height": "137","left": "56","surah": "4","top": "1162","width": "1002"},{"ayah": "25","block": "5","height": "136","left": "56","surah": "4","top": "1299","width": "1002"},{"ayah": "25","block": "6","height": "137","left": "56","surah": "4","top": "1435","width": "1002"},{"ayah": "25","block": "7","height": "137","left": "56","surah": "4","top": "1572","width": "1002"},{"ayah": "25","block": "8","height": "136","left": "56","surah": "4","top": "1709","width": "1002"},{"ayah": "26","block": "1","height": "135","left": "56","surah": "4","top": "1845","width": "1002"},{"ayah": "26","block": "2","height": "154","left": "56","surah": "4","top": "1980","width": "1002"}]}
