{"data": [{"ayah": "52","block": "1","height": "144","left": "20","surah": "15","top": "64","width": "1002"},{"ayah": "53","block": "1","height": "137","left": "310","surah": "15","top": "208","width": "712"},{"ayah": "54","block": "1","height": "137","left": "20","surah": "15","top": "208","width": "290"},{"ayah": "54","block": "2","height": "135","left": "383","surah": "15","top": "345","width": "639"},{"ayah": "55","block": "1","height": "135","left": "20","surah": "15","top": "345","width": "363"},{"ayah": "55","block": "2","height": "138","left": "504","surah": "15","top": "480","width": "518"},{"ayah": "56","block": "1","height": "138","left": "20","surah": "15","top": "480","width": "484"},{"ayah": "56","block": "2","height": "136","left": "581","surah": "15","top": "618","width": "441"},{"ayah": "57","block": "1","height": "136","left": "20","surah": "15","top": "618","width": "561"},{"ayah": "57","block": "2","height": "136","left": "922","surah": "15","top": "754","width": "100"},{"ayah": "58","block": "1","height": "136","left": "270","surah": "15","top": "754","width": "652"},{"ayah": "59","block": "1","height": "136","left": "20","surah": "15","top": "754","width": "250"},{"ayah": "59","block": "2","height": "137","left": "498","surah": "15","top": "890","width": "524"},{"ayah": "60","block": "1","height": "137","left": "20","surah": "15","top": "890","width": "478"},{"ayah": "60","block": "2","height": "135","left": "715","surah": "15","top": "1027","width": "307"},{"ayah": "61","block": "1","height": "135","left": "148","surah": "15","top": "1027","width": "567"},{"ayah": "62","block": "1","height": "135","left": "20","surah": "15","top": "1027","width": "128"},{"ayah": "62","block": "2","height": "137","left": "561","surah": "15","top": "1162","width": "461"},{"ayah": "63","block": "1","height": "137","left": "20","surah": "15","top": "1162","width": "541"},{"ayah": "63","block": "2","height": "136","left": "759","surah": "15","top": "1299","width": "263"},{"ayah": "64","block": "1","height": "136","left": "163","surah": "15","top": "1299","width": "596"},{"ayah": "65","block": "1","height": "136","left": "20","surah": "15","top": "1299","width": "143"},{"ayah": "65","block": "2","height": "137","left": "20","surah": "15","top": "1435","width": "1002"},{"ayah": "65","block": "3","height": "137","left": "562","surah": "15","top": "1572","width": "460"},{"ayah": "66","block": "1","height": "137","left": "20","surah": "15","top": "1572","width": "542"},{"ayah": "66","block": "2","height": "136","left": "433","surah": "15","top": "1709","width": "589"},{"ayah": "67","block": "1","height": "136","left": "20","surah": "15","top": "1709","width": "413"},{"ayah": "67","block": "2","height": "135","left": "777","surah": "15","top": "1845","width": "245"},{"ayah": "68","block": "1","height": "135","left": "182","surah": "15","top": "1845","width": "595"},{"ayah": "69","block": "1","height": "135","left": "20","surah": "15","top": "1845","width": "162"},{"ayah": "69","block": "2","height": "154","left": "703","surah": "15","top": "1980","width": "319"},{"ayah": "70","block": "1","height": "154","left": "20","surah": "15","top": "1980","width": "683"}]}
