{"data": [{"ayah": "14","block": "1","height": "144","left": "56","surah": "5","top": "64","width": "1002"},{"ayah": "14","block": "2","height": "137","left": "56","surah": "5","top": "208","width": "1002"},{"ayah": "14","block": "3","height": "135","left": "56","surah": "5","top": "345","width": "1002"},{"ayah": "14","block": "4","height": "138","left": "444","surah": "5","top": "480","width": "614"},{"ayah": "15","block": "1","height": "138","left": "56","surah": "5","top": "480","width": "388"},{"ayah": "15","block": "2","height": "136","left": "56","surah": "5","top": "618","width": "1002"},{"ayah": "15","block": "3","height": "136","left": "56","surah": "5","top": "754","width": "1002"},{"ayah": "15","block": "4","height": "137","left": "56","surah": "5","top": "890","width": "1002"},{"ayah": "15","block": "5","height": "135","left": "790","surah": "5","top": "1027","width": "268"},{"ayah": "16","block": "1","height": "135","left": "56","surah": "5","top": "1027","width": "734"},{"ayah": "16","block": "2","height": "137","left": "56","surah": "5","top": "1162","width": "1002"},{"ayah": "16","block": "3","height": "136","left": "56","surah": "5","top": "1299","width": "1002"},{"ayah": "16","block": "4","height": "137","left": "948","surah": "5","top": "1435","width": "110"},{"ayah": "17","block": "1","height": "137","left": "56","surah": "5","top": "1435","width": "892"},{"ayah": "17","block": "2","height": "137","left": "56","surah": "5","top": "1572","width": "1002"},{"ayah": "17","block": "3","height": "136","left": "56","surah": "5","top": "1709","width": "1002"},{"ayah": "17","block": "4","height": "135","left": "56","surah": "5","top": "1845","width": "1002"},{"ayah": "17","block": "5","height": "154","left": "56","surah": "5","top": "1980","width": "1002"}]}
