{"data":[{"ayah":"50","block":"1","height":"80.0","left":"352.0","surah":"17","top":"63.0","width":"353.0"},{"ayah":"51","block":"1","height":"80.0","left":"8.0","surah":"17","top":"63.0","width":"340.0"},{"ayah":"51","block":"2","height":"80.0","left":"8.0","surah":"17","top":"144.0","width":"748.0"},{"ayah":"51","block":"3","height":"80.0","left":"8.0","surah":"17","top":"225.0","width":"748.0"},{"ayah":"51","block":"4","height":"80.0","left":"558.0","surah":"17","top":"306.0","width":"198.0"},{"ayah":"52","block":"1","height":"80.0","left":"8.0","surah":"17","top":"306.0","width":"548.0"},{"ayah":"52","block":"2","height":"80.0","left":"457.0","surah":"17","top":"387.0","width":"299.0"},{"ayah":"53","block":"1","height":"80.0","left":"8.0","surah":"17","top":"387.0","width":"446.0"},{"ayah":"53","block":"2","height":"80.0","left":"8.0","surah":"17","top":"468.0","width":"748.0"},{"ayah":"53","block":"3","height":"80.0","left":"609.0","surah":"17","top":"549.0","width":"147.0"},{"ayah":"54","block":"1","height":"80.0","left":"8.0","surah":"17","top":"549.0","width":"601.0"},{"ayah":"54","block":"2","height":"80.0","left":"192.0","surah":"17","top":"630.0","width":"564.0"},{"ayah":"55","block":"1","height":"80.0","left":"8.0","surah":"17","top":"630.0","width":"183.0"},{"ayah":"55","block":"2","height":"80.0","left":"8.0","surah":"17","top":"711.0","width":"748.0"},{"ayah":"55","block":"3","height":"80.0","left":"368.0","surah":"17","top":"792.0","width":"388.0"},{"ayah":"56","block":"1","height":"80.0","left":"8.0","surah":"17","top":"792.0","width":"357.0"},{"ayah":"56","block":"2","height":"80.0","left":"103.0","surah":"17","top":"872.0","width":"653.0"},{"ayah":"57","block":"1","height":"80.0","left":"8.0","surah":"17","top":"872.0","width":"93.0"},{"ayah":"57","block":"2","height":"80.0","left":"8.0","surah":"17","top":"953.0","width":"748.0"},{"ayah":"57","block":"3","height":"80.0","left":"8.0","surah":"17","top":"1034.0","width":"748.0"},{"ayah":"57","block":"4","height":"80.0","left":"587.0","surah":"17","top":"1115.0","width":"169.0"},{"ayah":"58","block":"1","height":"80.0","left":"8.0","surah":"17","top":"1115.0","width":"579.0"},{"ayah":"58","block":"2","height":"87.0","left":"18.0","surah":"17","top":"1196.0","width":"738.0"}],"viewportHeight":"1327","viewportWidth":"800"}