{"data":[{"ayah":"53","block":"1","height":"80.0","left":"44.0","surah":"12","top":"63.0","width":"709.0"},{"ayah":"53","block":"2","height":"80.0","left":"478.0","surah":"12","top":"144.0","width":"314.0"},{"ayah":"54","block":"1","height":"80.0","left":"44.0","surah":"12","top":"144.0","width":"434.0"},{"ayah":"54","block":"2","height":"80.0","left":"56.0","surah":"12","top":"225.0","width":"736.0"},{"ayah":"55","block":"1","height":"80.0","left":"152.0","surah":"12","top":"306.0","width":"640.0"},{"ayah":"56","block":"1","height":"80.0","left":"44.0","surah":"12","top":"306.0","width":"109.0"},{"ayah":"56","block":"2","height":"80.0","left":"44.0","surah":"12","top":"387.0","width":"748.0"},{"ayah":"56","block":"3","height":"80.0","left":"154.0","surah":"12","top":"468.0","width":"638.0"},{"ayah":"57","block":"1","height":"80.0","left":"44.0","surah":"12","top":"468.0","width":"110.0"},{"ayah":"57","block":"2","height":"80.0","left":"148.0","surah":"12","top":"549.0","width":"644.0"},{"ayah":"58","block":"1","height":"80.0","left":"44.0","surah":"12","top":"549.0","width":"104.0"},{"ayah":"58","block":"2","height":"80.0","left":"44.0","surah":"12","top":"630.0","width":"748.0"},{"ayah":"58","block":"3","height":"80.0","left":"738.0","surah":"12","top":"711.0","width":"54.0"},{"ayah":"59","block":"1","height":"80.0","left":"44.0","surah":"12","top":"711.0","width":"694.0"},{"ayah":"59","block":"2","height":"80.0","left":"230.0","surah":"12","top":"792.0","width":"562.0"},{"ayah":"60","block":"1","height":"80.0","left":"44.0","surah":"12","top":"792.0","width":"186.0"},{"ayah":"60","block":"2","height":"80.0","left":"280.0","surah":"12","top":"873.0","width":"512.0"},{"ayah":"61","block":"1","height":"80.0","left":"44.0","surah":"12","top":"872.0","width":"237.0"},{"ayah":"61","block":"2","height":"80.0","left":"577.0","surah":"12","top":"954.0","width":"215.0"},{"ayah":"62","block":"1","height":"80.0","left":"44.0","surah":"12","top":"954.0","width":"535.0"},{"ayah":"62","block":"2","height":"80.0","left":"44.0","surah":"12","top":"1035.0","width":"748.0"},{"ayah":"62","block":"3","height":"80.0","left":"739.0","surah":"12","top":"1116.0","width":"65.0"},{"ayah":"63","block":"1","height":"80.0","left":"44.0","surah":"12","top":"1116.0","width":"693.0"},{"ayah":"63","block":"2","height":"87.0","left":"59.0","surah":"12","top":"1197.0","width":"733.0"}],"viewportHeight":"1327","viewportWidth":"800"}